{
  "type": "minecraft:crafting_shapeless",
  "ingredients": [
    {
      "item": "minecraft:nether_star"
    },
    {
      "item": "tinkers_ingenuity:ender_residual_interest"
    },
    {
      "item": "undergarden:forgotten_ingot"
    },
    {
      "item": "tinkersinnovation:hostilium_ingot"
    },
    {
      "item": "l2hostility:miracle_ingot"
    },
    {
      "item": "tconstruct:manyullyn_block"
    }
  ],
  "result": {
    "item": "tinkers_ingenuity:gleiter_ingot",
    "count": 2
  }
}